{
  "site_id": "house-efstratiou",
  "platform": "vrm",
  "updated_at": "2026-05-28T19:54:01+02:00",
  "current": {
    "power_kw": 0,
    "today_kwh": 13.194208145141602,
    "status": "offline",
    "status_severity": "info",
    "status_reason": "Outside daylight hours"
  },
  "energy": {
    "today": {
      "pv": 13.194208145141602,
      "consumption": 11.498573303222656,
      "import": 33.4051513671875,
      "export": 1.2743111848831177,
      "discharge": 7.549091339111328,
      "charge": 0.31496238708496094
    },
    "month": {
      "pv": 308.8173153400421,
      "consumption": 307.2654921039939,
      "import": 1443.0481725521386,
      "export": 85.59730576723814,
      "discharge": 196.47982162609696,
      "charge": 13.350198477506638
    },
    "year": {
      "pv": 1995.005948394537,
      "consumption": 2620.954738197848,
      "import": 6795.354744631797,
      "export": 273.266909878701,
      "discharge": 944.878779117018,
      "charge": 107.29092877730727
    },
    "lifetime": {
      "pv": 0.0,
      "consumption": 0.0,
      "import": 0.0,
      "export": 0.0,
      "discharge": 0.0,
      "charge": 0.0
    },
    "hourly": {
      "pv": [
        {
          "time": "2026-05-28 07:00:00",
          "value": 0.171875
        },
        {
          "time": "2026-05-28 08:00:00",
          "value": 1.30859375
        },
        {
          "time": "2026-05-28 09:00:00",
          "value": 2.4420089721679688
        },
        {
          "time": "2026-05-28 10:00:00",
          "value": 4.463275909423828
        },
        {
          "time": "2026-05-28 11:00:00",
          "value": 3.4720401763916016
        },
        {
          "time": "2026-05-28 12:00:00",
          "value": 0.7673492431640625
        },
        {
          "time": "2026-05-28 13:00:00",
          "value": 0.5182437896728516
        },
        {
          "time": "2026-05-28 14:00:00",
          "value": 0.05082130432128906
        }
      ],
      "consumption": [
        {
          "time": "2026-05-28 09:00:00",
          "value": 0.9466304779052734
        },
        {
          "time": "2026-05-28 10:00:00",
          "value": 1.5655841827392578
        },
        {
          "time": "2026-05-28 11:00:00",
          "value": 3.0947532653808594
        },
        {
          "time": "2026-05-28 12:00:00",
          "value": 1.9296703338623047
        },
        {
          "time": "2026-05-28 13:00:00",
          "value": 1.8750591278076172
        },
        {
          "time": "2026-05-28 14:00:00",
          "value": 1.5135726928710938
        },
        {
          "time": "2026-05-28 15:00:00",
          "value": 0.5015163421630859
        },
        {
          "time": "2026-05-28 16:00:00",
          "value": 0.07178688049316406
        }
      ],
      "import": [
        {
          "time": "2026-05-28 00:00:00",
          "value": 2.2573471069335938
        },
        {
          "time": "2026-05-28 01:00:00",
          "value": 2.29376220703125
        },
        {
          "time": "2026-05-28 02:00:00",
          "value": 3.6955032348632812
        },
        {
          "time": "2026-05-28 03:00:00",
          "value": 2.1663284301757812
        },
        {
          "time": "2026-05-28 04:00:00",
          "value": 2.311962127685547
        },
        {
          "time": "2026-05-28 05:00:00",
          "value": 2.1481246948242188
        },
        {
          "time": "2026-05-28 06:00:00",
          "value": 2.2209434509277344
        },
        {
          "time": "2026-05-28 07:00:00",
          "value": 2.494007110595703
        },
        {
          "time": "2026-05-28 08:00:00",
          "value": 2.2573509216308594
        },
        {
          "time": "2026-05-28 09:00:00",
          "value": 0.8920211791992188
        },
        {
          "time": "2026-05-28 10:00:00",
          "value": 0.6553573608398438
        },
        {
          "time": "2026-05-28 11:00:00",
          "value": 0.4369049072265625
        },
        {
          "time": "2026-05-28 13:00:00",
          "value": 0.2730674743652344
        },
        {
          "time": "2026-05-28 14:00:00",
          "value": 1.18328857421875
        },
        {
          "time": "2026-05-28 15:00:00",
          "value": 0.6371574401855469
        },
        {
          "time": "2026-05-28 16:00:00",
          "value": 0.4915199279785156
        },
        {
          "time": "2026-05-28 17:00:00",
          "value": 1.4563560485839844
        },
        {
          "time": "2026-05-28 18:00:00",
          "value": 3.6590957641601562
        },
        {
          "time": "2026-05-28 19:00:00",
          "value": 1.8750534057617188
        }
      ],
      "export": [
        {
          "time": "2026-05-28 00:00:00",
          "value": 0.12743103504180908
        },
        {
          "time": "2026-05-28 01:00:00",
          "value": 0.09102213382720947
        },
        {
          "time": "2026-05-28 02:00:00",
          "value": 0.10922670364379883
        },
        {
          "time": "2026-05-28 03:00:00",
          "value": 0.10922670364379883
        },
        {
          "time": "2026-05-28 04:00:00",
          "value": 0.09102225303649902
        },
        {
          "time": "2026-05-28 05:00:00",
          "value": 0.10922670364379883
        },
        {
          "time": "2026-05-28 06:00:00",
          "value": 0.10922658443450928
        },
        {
          "time": "2026-05-28 07:00:00",
          "value": 0.10922670364379883
        },
        {
          "time": "2026-05-28 08:00:00",
          "value": 0.10922670364379883
        },
        {
          "time": "2026-05-28 09:00:00",
          "value": 0.018204450607299805
        },
        {
          "time": "2026-05-28 17:00:00",
          "value": 0.07281780242919922
        },
        {
          "time": "2026-05-28 18:00:00",
          "value": 0.10922646522521973
        },
        {
          "time": "2026-05-28 19:00:00",
          "value": 0.10922694206237793
        }
      ],
      "charge": [
        {
          "time": "2026-05-28 15:00:00",
          "value": 0.036407470703125
        },
        {
          "time": "2026-05-28 16:00:00",
          "value": 0.1440105438232422
        },
        {
          "time": "2026-05-28 17:00:00",
          "value": 0.13454437255859375
        }
      ],
      "discharge": [
        {
          "time": "2026-05-28 09:00:00",
          "value": 0.010946273803710938
        },
        {
          "time": "2026-05-28 10:00:00",
          "value": 0.010168075561523438
        },
        {
          "time": "2026-05-28 12:00:00",
          "value": 0.007366180419921875
        },
        {
          "time": "2026-05-28 14:00:00",
          "value": 1.7996349334716797
        },
        {
          "time": "2026-05-28 15:00:00",
          "value": 2.684263229370117
        },
        {
          "time": "2026-05-28 16:00:00",
          "value": 2.526988983154297
        },
        {
          "time": "2026-05-28 17:00:00",
          "value": 0.4915199279785156
        },
        {
          "time": "2026-05-28 19:00:00",
          "value": 0.0182037353515625
        }
      ]
    }
  },
  "energy_powerflow_hourly": [
    {
      "time": "2026-05-28 00:00:00",
      "pv_to_load": 0.0,
      "pv_to_batt": 0.0,
      "pv_to_grid": 0.1274,
      "batt_to_load": 0.0,
      "batt_to_grid": 0.0,
      "grid_to_load": 2.2573,
      "grid_to_batt": 0.0,
      "self_consumed": 0.0,
      "self_sufficient": 0.0,
      "balance_error": 2.1299
    },
    {
      "time": "2026-05-28 01:00:00",
      "pv_to_load": 0.0,
      "pv_to_batt": 0.0,
      "pv_to_grid": 0.091,
      "batt_to_load": 0.0,
      "batt_to_grid": 0.0,
      "grid_to_load": 2.2938,
      "grid_to_batt": 0.0,
      "self_consumed": 0.0,
      "self_sufficient": 0.0,
      "balance_error": 2.2027
    },
    {
      "time": "2026-05-28 02:00:00",
      "pv_to_load": 0.0,
      "pv_to_batt": 0.0,
      "pv_to_grid": 0.1092,
      "batt_to_load": 0.0,
      "batt_to_grid": 0.0,
      "grid_to_load": 3.6955,
      "grid_to_batt": 0.0,
      "self_consumed": 0.0,
      "self_sufficient": 0.0,
      "balance_error": 3.5863
    },
    {
      "time": "2026-05-28 03:00:00",
      "pv_to_load": 0.0,
      "pv_to_batt": 0.0,
      "pv_to_grid": 0.1092,
      "batt_to_load": 0.0,
      "batt_to_grid": 0.0,
      "grid_to_load": 2.1663,
      "grid_to_batt": 0.0,
      "self_consumed": 0.0,
      "self_sufficient": 0.0,
      "balance_error": 2.0571
    },
    {
      "time": "2026-05-28 04:00:00",
      "pv_to_load": 0.0,
      "pv_to_batt": 0.0,
      "pv_to_grid": 0.091,
      "batt_to_load": 0.0,
      "batt_to_grid": 0.0,
      "grid_to_load": 2.312,
      "grid_to_batt": 0.0,
      "self_consumed": 0.0,
      "self_sufficient": 0.0,
      "balance_error": 2.2209
    },
    {
      "time": "2026-05-28 05:00:00",
      "pv_to_load": 0.0,
      "pv_to_batt": 0.0,
      "pv_to_grid": 0.1092,
      "batt_to_load": 0.0,
      "batt_to_grid": 0.0,
      "grid_to_load": 2.1481,
      "grid_to_batt": 0.0,
      "self_consumed": 0.0,
      "self_sufficient": 0.0,
      "balance_error": 2.0389
    },
    {
      "time": "2026-05-28 06:00:00",
      "pv_to_load": 0.0,
      "pv_to_batt": 0.0,
      "pv_to_grid": 0.1092,
      "batt_to_load": 0.0,
      "batt_to_grid": 0.0,
      "grid_to_load": 2.2209,
      "grid_to_batt": 0.0,
      "self_consumed": 0.0,
      "self_sufficient": 0.0,
      "balance_error": 2.1117
    },
    {
      "time": "2026-05-28 07:00:00",
      "pv_to_load": 0.0,
      "pv_to_batt": 0.0,
      "pv_to_grid": 0.1092,
      "batt_to_load": 0.0,
      "batt_to_grid": 0.0,
      "grid_to_load": 2.494,
      "grid_to_batt": 0.0,
      "self_consumed": 0.0,
      "self_sufficient": 0.0,
      "balance_error": 2.5567
    },
    {
      "time": "2026-05-28 08:00:00",
      "pv_to_load": 0.0,
      "pv_to_batt": 0.0,
      "pv_to_grid": 0.1092,
      "batt_to_load": 0.0,
      "batt_to_grid": 0.0,
      "grid_to_load": 2.2574,
      "grid_to_batt": 0.0,
      "self_consumed": 0.0,
      "self_sufficient": 0.0,
      "balance_error": 3.4567
    },
    {
      "time": "2026-05-28 09:00:00",
      "pv_to_load": 0.9357,
      "pv_to_batt": 0.0,
      "pv_to_grid": 0.0182,
      "batt_to_load": 0.0109,
      "batt_to_grid": 0.0,
      "grid_to_load": 0.892,
      "grid_to_batt": 0.0,
      "self_consumed": 0.9466,
      "self_sufficient": 0.0577,
      "balance_error": 2.3801
    },
    {
      "time": "2026-05-28 10:00:00",
      "pv_to_load": 1.5554,
      "pv_to_batt": 0.0,
      "pv_to_grid": 0.0,
      "batt_to_load": 0.0102,
      "batt_to_grid": 0.0,
      "grid_to_load": 0.6554,
      "grid_to_batt": 0.0,
      "self_consumed": 1.5656,
      "self_sufficient": 0.5814,
      "balance_error": 3.5632
    },
    {
      "time": "2026-05-28 11:00:00",
      "pv_to_load": 3.0948,
      "pv_to_batt": 0.0,
      "pv_to_grid": 0.0,
      "batt_to_load": 0.0,
      "batt_to_grid": 0.0,
      "grid_to_load": 0.4369,
      "grid_to_batt": 0.0,
      "self_consumed": 3.0948,
      "self_sufficient": 0.8588,
      "balance_error": 0.8142
    },
    {
      "time": "2026-05-28 12:00:00",
      "pv_to_load": 0.7673,
      "pv_to_batt": 0.0,
      "pv_to_grid": 0.0,
      "batt_to_load": 0.0074,
      "batt_to_grid": 0.0,
      "grid_to_load": 0.0,
      "grid_to_batt": 0.0,
      "self_consumed": 0.7747,
      "self_sufficient": 1.0,
      "balance_error": -1.155
    },
    {
      "time": "2026-05-28 13:00:00",
      "pv_to_load": 0.5182,
      "pv_to_batt": 0.0,
      "pv_to_grid": 0.0,
      "batt_to_load": 0.0,
      "batt_to_grid": 0.0,
      "grid_to_load": 0.2731,
      "grid_to_batt": 0.0,
      "self_consumed": 0.5182,
      "self_sufficient": 0.8544,
      "balance_error": -1.0837
    },
    {
      "time": "2026-05-28 14:00:00",
      "pv_to_load": 0.0508,
      "pv_to_batt": 0.0,
      "pv_to_grid": 0.0,
      "batt_to_load": 0.3303,
      "batt_to_grid": 1.4694,
      "grid_to_load": 1.1833,
      "grid_to_batt": 0.0,
      "self_consumed": 0.3811,
      "self_sufficient": 0.2182,
      "balance_error": 1.5202
    },
    {
      "time": "2026-05-28 15:00:00",
      "pv_to_load": 0.0,
      "pv_to_batt": 0.0,
      "pv_to_grid": 0.0,
      "batt_to_load": 0.0,
      "batt_to_grid": 2.6843,
      "grid_to_load": 0.6007,
      "grid_to_batt": 0.0364,
      "self_consumed": 0.0,
      "self_sufficient": -0.1979,
      "balance_error": 2.7835
    },
    {
      "time": "2026-05-28 16:00:00",
      "pv_to_load": 0.0,
      "pv_to_batt": 0.0,
      "pv_to_grid": 0.0,
      "batt_to_load": 0.0,
      "batt_to_grid": 2.527,
      "grid_to_load": 0.3475,
      "grid_to_batt": 0.144,
      "self_consumed": 0.0,
      "self_sufficient": -3.8408,
      "balance_error": 2.8027
    },
    {
      "time": "2026-05-28 17:00:00",
      "pv_to_load": 0.0,
      "pv_to_batt": 0.0,
      "pv_to_grid": 0.0,
      "batt_to_load": 0.0,
      "batt_to_grid": 0.4915,
      "grid_to_load": 1.3218,
      "grid_to_batt": 0.1345,
      "self_consumed": 0.0,
      "self_sufficient": 0.0,
      "balance_error": 1.7405
    },
    {
      "time": "2026-05-28 18:00:00",
      "pv_to_load": 0.0,
      "pv_to_batt": 0.0,
      "pv_to_grid": 0.1092,
      "batt_to_load": 0.0,
      "batt_to_grid": 0.0,
      "grid_to_load": 3.6591,
      "grid_to_batt": 0.0,
      "self_consumed": 0.0,
      "self_sufficient": 0.0,
      "balance_error": 3.5499
    },
    {
      "time": "2026-05-28 19:00:00",
      "pv_to_load": 0.0,
      "pv_to_batt": 0.0,
      "pv_to_grid": 0.091,
      "batt_to_load": 0.0,
      "batt_to_grid": 0.0182,
      "grid_to_load": 1.8751,
      "grid_to_batt": 0.0,
      "self_consumed": 0.0,
      "self_sufficient": 0.0,
      "balance_error": 1.784
    }
  ],
  "irradiation": null,
  "irradiation_forecast": null,
  "financial": null,
  "performance": {
    "method": "empirical",
    "hourly_expected": [],
    "today_expected_total": 0.0,
    "today_actual_total": 0.0,
    "performance_pct": null,
    "elapsed_hours_compared": 0,
    "reason": "Expected = site's own 30-day average for this hour-of-day"
  }
}
