{
  "site_id": "rdm-somerset-west-6mwh-bess",
  "name": "RDM Somerset West 6MWh BESS",
  "platform": "fusionsolar",
  "capacity_kwp": null,
  "updated_at": "2026-07-22T11:03:52+02:00",
  "current": {
    "power_kw": null,
    "today_kwh": 0.0,
    "month_kwh": 0.0,
    "total_kwh": 0.0,
    "status": "underperforming",
    "status_severity": "warn",
    "status_reason": "Zero PV across daylight hours despite reporting."
  },
  "today_hourly": [
    {
      "time": "2026-07-22 00:00:00",
      "pv_kwh": 0.0
    },
    {
      "time": "2026-07-22 01:00:00",
      "pv_kwh": 0.0
    },
    {
      "time": "2026-07-22 02:00:00",
      "pv_kwh": 0.0
    },
    {
      "time": "2026-07-22 03:00:00",
      "pv_kwh": 0.0
    },
    {
      "time": "2026-07-22 04:00:00",
      "pv_kwh": 0.0
    },
    {
      "time": "2026-07-22 05:00:00",
      "pv_kwh": 0.0
    },
    {
      "time": "2026-07-22 06:00:00",
      "pv_kwh": 0.0
    },
    {
      "time": "2026-07-22 07:00:00",
      "pv_kwh": 0.0
    },
    {
      "time": "2026-07-22 08:00:00",
      "pv_kwh": 0.0
    },
    {
      "time": "2026-07-22 09:00:00",
      "pv_kwh": 0.0
    }
  ],
  "irradiation": {
    "source": "open-meteo",
    "today_total": 2.835,
    "today_hourly": [
      {
        "time": "2026-07-22 00:00:00",
        "value": 0.0
      },
      {
        "time": "2026-07-22 01:00:00",
        "value": 0.0
      },
      {
        "time": "2026-07-22 02:00:00",
        "value": 0.0
      },
      {
        "time": "2026-07-22 03:00:00",
        "value": 0.0
      },
      {
        "time": "2026-07-22 04:00:00",
        "value": 0.0
      },
      {
        "time": "2026-07-22 05:00:00",
        "value": 0.0
      },
      {
        "time": "2026-07-22 06:00:00",
        "value": 0.0
      },
      {
        "time": "2026-07-22 07:00:00",
        "value": 0.0
      },
      {
        "time": "2026-07-22 08:00:00",
        "value": 1.0
      },
      {
        "time": "2026-07-22 09:00:00",
        "value": 89.0
      },
      {
        "time": "2026-07-22 10:00:00",
        "value": 246.0
      },
      {
        "time": "2026-07-22 11:00:00",
        "value": 376.0
      },
      {
        "time": "2026-07-22 12:00:00",
        "value": 480.0
      },
      {
        "time": "2026-07-22 13:00:00",
        "value": 488.0
      },
      {
        "time": "2026-07-22 14:00:00",
        "value": 491.0
      },
      {
        "time": "2026-07-22 15:00:00",
        "value": 195.0
      },
      {
        "time": "2026-07-22 16:00:00",
        "value": 263.0
      },
      {
        "time": "2026-07-22 17:00:00",
        "value": 177.0
      },
      {
        "time": "2026-07-22 18:00:00",
        "value": 29.0
      },
      {
        "time": "2026-07-22 19:00:00",
        "value": 0.0
      },
      {
        "time": "2026-07-22 20:00:00",
        "value": 0.0
      },
      {
        "time": "2026-07-22 21:00:00",
        "value": 0.0
      },
      {
        "time": "2026-07-22 22:00:00",
        "value": 0.0
      },
      {
        "time": "2026-07-22 23:00:00",
        "value": 0.0
      }
    ]
  },
  "energy": {
    "today": {
      "pv": 0.0,
      "import": 0.0,
      "export": 0.0,
      "charge": 3028.85,
      "discharge": 4494.32,
      "consumption": 4469.43,
      "pv_to_load": 0.0,
      "pv_to_batt": 0.0,
      "pv_to_grid": 0.0,
      "batt_to_load": 4469.43,
      "batt_to_grid": 24.89,
      "grid_to_load": 0.0,
      "grid_to_batt": 3028.85,
      "self_consumed": 4469.43
    },
    "month": {
      "pv": 0.0,
      "import": 0.0,
      "export": 0.0,
      "charge": 146957.49,
      "discharge": 139892.72,
      "consumption": 0.0,
      "pv_to_load": 0.0,
      "pv_to_batt": 0.0,
      "pv_to_grid": 0.0,
      "batt_to_load": 0.0,
      "batt_to_grid": 139892.72,
      "grid_to_load": 0.0,
      "grid_to_batt": 146957.49,
      "self_consumed": 0.0
    },
    "year": {
      "pv": 0.0,
      "import": 0.0,
      "export": 0.0,
      "charge": 1031272.38,
      "discharge": 989662.84,
      "consumption": 0.0,
      "pv_to_load": 0.0,
      "pv_to_batt": 0.0,
      "pv_to_grid": 0.0,
      "batt_to_load": 0.0,
      "batt_to_grid": 989662.84,
      "grid_to_load": 0.0,
      "grid_to_batt": 1031272.38,
      "self_consumed": 0.0
    },
    "lifetime": {
      "pv": 0.0,
      "import": 0.0,
      "export": 0.0,
      "charge": 2133646.21,
      "discharge": 2038173.23,
      "consumption": 0.0,
      "pv_to_load": 0.0,
      "pv_to_batt": 0.0,
      "pv_to_grid": 0.0,
      "batt_to_load": 0.0,
      "batt_to_grid": 2038173.23,
      "grid_to_load": 0.0,
      "grid_to_batt": 2133646.21,
      "self_consumed": 0.0
    },
    "hourly": {
      "pv": [
        {
          "time": "2026-07-22 00:00:00",
          "value": 0.0
        },
        {
          "time": "2026-07-22 01:00:00",
          "value": 0.0
        },
        {
          "time": "2026-07-22 02:00:00",
          "value": 0.0
        },
        {
          "time": "2026-07-22 03:00:00",
          "value": 0.0
        },
        {
          "time": "2026-07-22 04:00:00",
          "value": 0.0
        },
        {
          "time": "2026-07-22 05:00:00",
          "value": 0.0
        },
        {
          "time": "2026-07-22 06:00:00",
          "value": 0.0
        },
        {
          "time": "2026-07-22 07:00:00",
          "value": 0.0
        },
        {
          "time": "2026-07-22 08:00:00",
          "value": 0.0
        },
        {
          "time": "2026-07-22 09:00:00",
          "value": 0.0
        }
      ],
      "import": [
        {
          "time": "2026-07-22 00:00:00",
          "value": 0.0
        },
        {
          "time": "2026-07-22 01:00:00",
          "value": 0.0
        },
        {
          "time": "2026-07-22 02:00:00",
          "value": 0.0
        },
        {
          "time": "2026-07-22 03:00:00",
          "value": 0.0
        },
        {
          "time": "2026-07-22 04:00:00",
          "value": 0.0
        },
        {
          "time": "2026-07-22 05:00:00",
          "value": 0.0
        },
        {
          "time": "2026-07-22 06:00:00",
          "value": 0.0
        },
        {
          "time": "2026-07-22 07:00:00",
          "value": 0.0
        },
        {
          "time": "2026-07-22 08:00:00",
          "value": 0.0
        },
        {
          "time": "2026-07-22 09:00:00",
          "value": 0.0
        }
      ],
      "export": [
        {
          "time": "2026-07-22 00:00:00",
          "value": 0.0
        },
        {
          "time": "2026-07-22 01:00:00",
          "value": 0.0
        },
        {
          "time": "2026-07-22 02:00:00",
          "value": 0.0
        },
        {
          "time": "2026-07-22 03:00:00",
          "value": 0.0
        },
        {
          "time": "2026-07-22 04:00:00",
          "value": 0.0
        },
        {
          "time": "2026-07-22 05:00:00",
          "value": 0.0
        },
        {
          "time": "2026-07-22 06:00:00",
          "value": 0.0
        },
        {
          "time": "2026-07-22 07:00:00",
          "value": 0.0
        },
        {
          "time": "2026-07-22 08:00:00",
          "value": 0.0
        },
        {
          "time": "2026-07-22 09:00:00",
          "value": 0.0
        }
      ],
      "charge": [
        {
          "time": "2026-07-22 00:00:00",
          "value": 1170.71
        },
        {
          "time": "2026-07-22 01:00:00",
          "value": 1173.62
        },
        {
          "time": "2026-07-22 02:00:00",
          "value": 660.95
        },
        {
          "time": "2026-07-22 03:00:00",
          "value": 2.94
        },
        {
          "time": "2026-07-22 04:00:00",
          "value": 1.85
        },
        {
          "time": "2026-07-22 05:00:00",
          "value": 1.57
        },
        {
          "time": "2026-07-22 06:00:00",
          "value": 0.03
        },
        {
          "time": "2026-07-22 07:00:00",
          "value": 0.0
        },
        {
          "time": "2026-07-22 08:00:00",
          "value": 9.56
        },
        {
          "time": "2026-07-22 09:00:00",
          "value": 7.62
        }
      ],
      "discharge": [
        {
          "time": "2026-07-22 00:00:00",
          "value": 0.0
        },
        {
          "time": "2026-07-22 01:00:00",
          "value": 0.0
        },
        {
          "time": "2026-07-22 02:00:00",
          "value": 1.32
        },
        {
          "time": "2026-07-22 03:00:00",
          "value": 3.93
        },
        {
          "time": "2026-07-22 04:00:00",
          "value": 5.71
        },
        {
          "time": "2026-07-22 05:00:00",
          "value": 6.25
        },
        {
          "time": "2026-07-22 06:00:00",
          "value": 2071.6
        },
        {
          "time": "2026-07-22 07:00:00",
          "value": 2377.82
        },
        {
          "time": "2026-07-22 08:00:00",
          "value": 19.33
        },
        {
          "time": "2026-07-22 09:00:00",
          "value": 8.36
        }
      ]
    },
    "powerflow_hourly": [
      {
        "time": "2026-07-22 00:00:00",
        "pv_to_load": 0.0,
        "pv_to_batt": 0.0,
        "pv_to_grid": 0.0,
        "batt_to_load": 0.0,
        "batt_to_grid": 0.0,
        "grid_to_load": 0.0,
        "grid_to_batt": 1170.71
      },
      {
        "time": "2026-07-22 01:00:00",
        "pv_to_load": 0.0,
        "pv_to_batt": 0.0,
        "pv_to_grid": 0.0,
        "batt_to_load": 0.0,
        "batt_to_grid": 0.0,
        "grid_to_load": 0.0,
        "grid_to_batt": 1173.62
      },
      {
        "time": "2026-07-22 02:00:00",
        "pv_to_load": 0.0,
        "pv_to_batt": 0.0,
        "pv_to_grid": 0.0,
        "batt_to_load": 0.0,
        "batt_to_grid": 1.32,
        "grid_to_load": 0.0,
        "grid_to_batt": 660.95
      },
      {
        "time": "2026-07-22 03:00:00",
        "pv_to_load": 0.0,
        "pv_to_batt": 0.0,
        "pv_to_grid": 0.0,
        "batt_to_load": 0.99,
        "batt_to_grid": 2.94,
        "grid_to_load": 0.0,
        "grid_to_batt": 2.94
      },
      {
        "time": "2026-07-22 04:00:00",
        "pv_to_load": 0.0,
        "pv_to_batt": 0.0,
        "pv_to_grid": 0.0,
        "batt_to_load": 3.86,
        "batt_to_grid": 1.85,
        "grid_to_load": 0.0,
        "grid_to_batt": 1.85
      },
      {
        "time": "2026-07-22 05:00:00",
        "pv_to_load": 0.0,
        "pv_to_batt": 0.0,
        "pv_to_grid": 0.0,
        "batt_to_load": 4.68,
        "batt_to_grid": 1.57,
        "grid_to_load": 0.0,
        "grid_to_batt": 1.57
      },
      {
        "time": "2026-07-22 06:00:00",
        "pv_to_load": 0.0,
        "pv_to_batt": 0.0,
        "pv_to_grid": 0.0,
        "batt_to_load": 2071.57,
        "batt_to_grid": 0.03,
        "grid_to_load": 0.0,
        "grid_to_batt": 0.03
      },
      {
        "time": "2026-07-22 07:00:00",
        "pv_to_load": 0.0,
        "pv_to_batt": 0.0,
        "pv_to_grid": 0.0,
        "batt_to_load": 2377.82,
        "batt_to_grid": 0.0,
        "grid_to_load": 0.0,
        "grid_to_batt": 0.0
      },
      {
        "time": "2026-07-22 08:00:00",
        "pv_to_load": 0.0,
        "pv_to_batt": 0.0,
        "pv_to_grid": 0.0,
        "batt_to_load": 9.77,
        "batt_to_grid": 9.56,
        "grid_to_load": 0.0,
        "grid_to_batt": 9.56
      },
      {
        "time": "2026-07-22 09:00:00",
        "pv_to_load": 0.0,
        "pv_to_batt": 0.0,
        "pv_to_grid": 0.0,
        "batt_to_load": 0.74,
        "batt_to_grid": 7.62,
        "grid_to_load": 0.0,
        "grid_to_batt": 7.62
      }
    ]
  },
  "financial": null,
  "performance": {
    "method": "empirical",
    "hourly_expected": [],
    "today_expected_total": 0.0,
    "today_actual_total": 0.0,
    "performance_pct": null,
    "elapsed_hours_compared": 0,
    "reason": "Expected = site's own 30-day average for this hour-of-day"
  },
  "irradiation_forecast": {
    "date": "2026-07-23",
    "total_forecast": 0.887,
    "hourly": [
      {
        "time": "2026-07-23 00:00:00",
        "value": 0.0
      },
      {
        "time": "2026-07-23 01:00:00",
        "value": 0.0
      },
      {
        "time": "2026-07-23 02:00:00",
        "value": 0.0
      },
      {
        "time": "2026-07-23 03:00:00",
        "value": 0.0
      },
      {
        "time": "2026-07-23 04:00:00",
        "value": 0.0
      },
      {
        "time": "2026-07-23 05:00:00",
        "value": 0.0
      },
      {
        "time": "2026-07-23 06:00:00",
        "value": 0.0
      },
      {
        "time": "2026-07-23 07:00:00",
        "value": 0.0
      },
      {
        "time": "2026-07-23 08:00:00",
        "value": 0.0
      },
      {
        "time": "2026-07-23 09:00:00",
        "value": 22.0
      },
      {
        "time": "2026-07-23 10:00:00",
        "value": 38.0
      },
      {
        "time": "2026-07-23 11:00:00",
        "value": 57.0
      },
      {
        "time": "2026-07-23 12:00:00",
        "value": 124.0
      },
      {
        "time": "2026-07-23 13:00:00",
        "value": 109.0
      },
      {
        "time": "2026-07-23 14:00:00",
        "value": 68.0
      },
      {
        "time": "2026-07-23 15:00:00",
        "value": 134.0
      },
      {
        "time": "2026-07-23 16:00:00",
        "value": 170.0
      },
      {
        "time": "2026-07-23 17:00:00",
        "value": 131.0
      },
      {
        "time": "2026-07-23 18:00:00",
        "value": 34.0
      },
      {
        "time": "2026-07-23 19:00:00",
        "value": 0.0
      },
      {
        "time": "2026-07-23 20:00:00",
        "value": 0.0
      },
      {
        "time": "2026-07-23 21:00:00",
        "value": 0.0
      },
      {
        "time": "2026-07-23 22:00:00",
        "value": 0.0
      },
      {
        "time": "2026-07-23 23:00:00",
        "value": 0.0
      }
    ]
  }
}
