{
  "site_id": "beyond-buds-mypower24",
  "platform": "mypower24",
  "updated_at": "2026-06-23T18:32:35+02:00",
  "current": {
    "power_kw": 18.0,
    "today_kwh": 3509.0,
    "status": "online",
    "status_severity": "ok",
    "status_reason": "Generating normally",
    "battery_soc": null,
    "grid_power_kw": null
  },
  "energy": {
    "today": {
      "pv": 3509.0,
      "consumption": 11476.69,
      "import": 8319.56,
      "export": 0.0,
      "charge": 0.0,
      "discharge": 0.0
    },
    "month": {
      "pv": 3509.0,
      "consumption": 11476.69,
      "import": 8319.56,
      "export": 0.0,
      "charge": 0.0,
      "discharge": 0.0
    },
    "year": {
      "pv": 3509.0,
      "consumption": 11476.69,
      "import": 8319.56,
      "export": 0.0,
      "charge": 0.0,
      "discharge": 0.0
    },
    "lifetime": {
      "pv": 3509.0,
      "consumption": 11476.69,
      "import": 8319.56,
      "export": 0.0,
      "charge": 0.0,
      "discharge": 0.0
    },
    "hourly": {
      "pv": [
        {
          "time": "2026-06-23 00:00:00",
          "value": 0.0
        },
        {
          "time": "2026-06-23 01:00:00",
          "value": 0.0
        },
        {
          "time": "2026-06-23 02:00:00",
          "value": 0.0
        },
        {
          "time": "2026-06-23 03:00:00",
          "value": 0.0
        },
        {
          "time": "2026-06-23 04:00:00",
          "value": 0.0
        },
        {
          "time": "2026-06-23 05:00:00",
          "value": 0.0
        },
        {
          "time": "2026-06-23 06:00:00",
          "value": 0.0
        },
        {
          "time": "2026-06-23 07:00:00",
          "value": 3.0
        },
        {
          "time": "2026-06-23 08:00:00",
          "value": 158.0
        },
        {
          "time": "2026-06-23 09:00:00",
          "value": 382.0
        },
        {
          "time": "2026-06-23 10:00:00",
          "value": 626.0
        },
        {
          "time": "2026-06-23 11:00:00",
          "value": 706.0
        },
        {
          "time": "2026-06-23 12:00:00",
          "value": 542.0
        },
        {
          "time": "2026-06-23 13:00:00",
          "value": 483.0
        },
        {
          "time": "2026-06-23 14:00:00",
          "value": 328.0
        },
        {
          "time": "2026-06-23 15:00:00",
          "value": 175.0
        },
        {
          "time": "2026-06-23 16:00:00",
          "value": 88.0
        },
        {
          "time": "2026-06-23 17:00:00",
          "value": 18.0
        },
        {
          "time": "2026-06-23 18:00:00",
          "value": 0.0
        }
      ],
      "consumption": [
        {
          "time": "2026-06-23 00:00:00",
          "value": 399.1
        },
        {
          "time": "2026-06-23 01:00:00",
          "value": 371.39
        },
        {
          "time": "2026-06-23 02:00:00",
          "value": 439.67
        },
        {
          "time": "2026-06-23 03:00:00",
          "value": 467.72
        },
        {
          "time": "2026-06-23 04:00:00",
          "value": 451.6
        },
        {
          "time": "2026-06-23 05:00:00",
          "value": 470.67
        },
        {
          "time": "2026-06-23 06:00:00",
          "value": 518.49
        },
        {
          "time": "2026-06-23 07:00:00",
          "value": 699.2
        },
        {
          "time": "2026-06-23 08:00:00",
          "value": 745.68
        },
        {
          "time": "2026-06-23 09:00:00",
          "value": 726.93
        },
        {
          "time": "2026-06-23 10:00:00",
          "value": 732.15
        },
        {
          "time": "2026-06-23 11:00:00",
          "value": 753.92
        },
        {
          "time": "2026-06-23 12:00:00",
          "value": 780.78
        },
        {
          "time": "2026-06-23 13:00:00",
          "value": 776.97
        },
        {
          "time": "2026-06-23 14:00:00",
          "value": 752.01
        },
        {
          "time": "2026-06-23 15:00:00",
          "value": 749.68
        },
        {
          "time": "2026-06-23 16:00:00",
          "value": 731.17
        },
        {
          "time": "2026-06-23 17:00:00",
          "value": 755.25
        },
        {
          "time": "2026-06-23 18:00:00",
          "value": 154.31
        }
      ],
      "import": [
        {
          "time": "2026-06-23 00:00:00",
          "value": 473.71
        },
        {
          "time": "2026-06-23 01:00:00",
          "value": 469.9
        },
        {
          "time": "2026-06-23 02:00:00",
          "value": 469.35
        },
        {
          "time": "2026-06-23 03:00:00",
          "value": 474.36
        },
        {
          "time": "2026-06-23 04:00:00",
          "value": 469.51
        },
        {
          "time": "2026-06-23 05:00:00",
          "value": 470.09
        },
        {
          "time": "2026-06-23 06:00:00",
          "value": 474.33
        },
        {
          "time": "2026-06-23 07:00:00",
          "value": 470.41
        },
        {
          "time": "2026-06-23 08:00:00",
          "value": 470.38
        },
        {
          "time": "2026-06-23 09:00:00",
          "value": 453.21
        },
        {
          "time": "2026-06-23 10:00:00",
          "value": 474.16
        },
        {
          "time": "2026-06-23 11:00:00",
          "value": 473.74
        },
        {
          "time": "2026-06-23 12:00:00",
          "value": 407.93
        },
        {
          "time": "2026-06-23 13:00:00",
          "value": 331.2
        },
        {
          "time": "2026-06-23 14:00:00",
          "value": 410.83
        },
        {
          "time": "2026-06-23 15:00:00",
          "value": 470.68
        },
        {
          "time": "2026-06-23 16:00:00",
          "value": 474.18
        },
        {
          "time": "2026-06-23 17:00:00",
          "value": 470.12
        },
        {
          "time": "2026-06-23 18:00:00",
          "value": 111.47
        }
      ],
      "export": [
        {
          "time": "2026-06-23 00:00:00",
          "value": 0.0
        },
        {
          "time": "2026-06-23 01:00:00",
          "value": 0.0
        },
        {
          "time": "2026-06-23 02:00:00",
          "value": 0.0
        },
        {
          "time": "2026-06-23 03:00:00",
          "value": 0.0
        },
        {
          "time": "2026-06-23 04:00:00",
          "value": 0.0
        },
        {
          "time": "2026-06-23 05:00:00",
          "value": 0.0
        },
        {
          "time": "2026-06-23 06:00:00",
          "value": 0.0
        },
        {
          "time": "2026-06-23 07:00:00",
          "value": 0.0
        },
        {
          "time": "2026-06-23 08:00:00",
          "value": 0.0
        },
        {
          "time": "2026-06-23 09:00:00",
          "value": 0.0
        },
        {
          "time": "2026-06-23 10:00:00",
          "value": 0.0
        },
        {
          "time": "2026-06-23 11:00:00",
          "value": 0.0
        },
        {
          "time": "2026-06-23 12:00:00",
          "value": 0.0
        },
        {
          "time": "2026-06-23 13:00:00",
          "value": 0.0
        },
        {
          "time": "2026-06-23 14:00:00",
          "value": 0.0
        },
        {
          "time": "2026-06-23 15:00:00",
          "value": 0.0
        },
        {
          "time": "2026-06-23 16:00:00",
          "value": 0.0
        },
        {
          "time": "2026-06-23 17:00:00",
          "value": 0.0
        },
        {
          "time": "2026-06-23 18:00:00",
          "value": 0.0
        }
      ],
      "charge": [
        {
          "time": "2026-06-23 00:00:00",
          "value": 0.0
        },
        {
          "time": "2026-06-23 01:00:00",
          "value": 0.0
        },
        {
          "time": "2026-06-23 02:00:00",
          "value": 0.0
        },
        {
          "time": "2026-06-23 03:00:00",
          "value": 0.0
        },
        {
          "time": "2026-06-23 04:00:00",
          "value": 0.0
        },
        {
          "time": "2026-06-23 05:00:00",
          "value": 0.0
        },
        {
          "time": "2026-06-23 06:00:00",
          "value": 0.0
        },
        {
          "time": "2026-06-23 07:00:00",
          "value": 0.0
        },
        {
          "time": "2026-06-23 08:00:00",
          "value": 0.0
        },
        {
          "time": "2026-06-23 09:00:00",
          "value": 0.0
        },
        {
          "time": "2026-06-23 10:00:00",
          "value": 0.0
        },
        {
          "time": "2026-06-23 11:00:00",
          "value": 0.0
        },
        {
          "time": "2026-06-23 12:00:00",
          "value": 0.0
        },
        {
          "time": "2026-06-23 13:00:00",
          "value": 0.0
        },
        {
          "time": "2026-06-23 14:00:00",
          "value": 0.0
        },
        {
          "time": "2026-06-23 15:00:00",
          "value": 0.0
        },
        {
          "time": "2026-06-23 16:00:00",
          "value": 0.0
        },
        {
          "time": "2026-06-23 17:00:00",
          "value": 0.0
        },
        {
          "time": "2026-06-23 18:00:00",
          "value": 0.0
        }
      ],
      "discharge": [
        {
          "time": "2026-06-23 00:00:00",
          "value": 0.0
        },
        {
          "time": "2026-06-23 01:00:00",
          "value": 0.0
        },
        {
          "time": "2026-06-23 02:00:00",
          "value": 0.0
        },
        {
          "time": "2026-06-23 03:00:00",
          "value": 0.0
        },
        {
          "time": "2026-06-23 04:00:00",
          "value": 0.0
        },
        {
          "time": "2026-06-23 05:00:00",
          "value": 0.0
        },
        {
          "time": "2026-06-23 06:00:00",
          "value": 0.0
        },
        {
          "time": "2026-06-23 07:00:00",
          "value": 0.0
        },
        {
          "time": "2026-06-23 08:00:00",
          "value": 0.0
        },
        {
          "time": "2026-06-23 09:00:00",
          "value": 0.0
        },
        {
          "time": "2026-06-23 10:00:00",
          "value": 0.0
        },
        {
          "time": "2026-06-23 11:00:00",
          "value": 0.0
        },
        {
          "time": "2026-06-23 12:00:00",
          "value": 0.0
        },
        {
          "time": "2026-06-23 13:00:00",
          "value": 0.0
        },
        {
          "time": "2026-06-23 14:00:00",
          "value": 0.0
        },
        {
          "time": "2026-06-23 15:00:00",
          "value": 0.0
        },
        {
          "time": "2026-06-23 16:00:00",
          "value": 0.0
        },
        {
          "time": "2026-06-23 17:00:00",
          "value": 0.0
        },
        {
          "time": "2026-06-23 18:00:00",
          "value": 0.0
        }
      ]
    }
  },
  "energy_powerflow_hourly": [
    {
      "time": "2026-06-23 00:00:00",
      "pv_to_load": 0.0,
      "pv_to_batt": 0.0,
      "pv_to_grid": 0.0,
      "batt_to_load": 0.0,
      "batt_to_grid": 0.0,
      "grid_to_load": 473.71,
      "grid_to_batt": 0.0,
      "self_consumed": 0.0,
      "self_sufficient": -0.1869,
      "balance_error": 74.61
    },
    {
      "time": "2026-06-23 01:00:00",
      "pv_to_load": 0.0,
      "pv_to_batt": 0.0,
      "pv_to_grid": 0.0,
      "batt_to_load": 0.0,
      "batt_to_grid": 0.0,
      "grid_to_load": 469.9,
      "grid_to_batt": 0.0,
      "self_consumed": 0.0,
      "self_sufficient": -0.2652,
      "balance_error": 98.51
    },
    {
      "time": "2026-06-23 02:00:00",
      "pv_to_load": 0.0,
      "pv_to_batt": 0.0,
      "pv_to_grid": 0.0,
      "batt_to_load": 0.0,
      "batt_to_grid": 0.0,
      "grid_to_load": 469.35,
      "grid_to_batt": 0.0,
      "self_consumed": 0.0,
      "self_sufficient": -0.0675,
      "balance_error": 29.68
    },
    {
      "time": "2026-06-23 03:00:00",
      "pv_to_load": 0.0,
      "pv_to_batt": 0.0,
      "pv_to_grid": 0.0,
      "batt_to_load": 0.0,
      "batt_to_grid": 0.0,
      "grid_to_load": 474.36,
      "grid_to_batt": 0.0,
      "self_consumed": 0.0,
      "self_sufficient": -0.0142,
      "balance_error": 6.64
    },
    {
      "time": "2026-06-23 04:00:00",
      "pv_to_load": 0.0,
      "pv_to_batt": 0.0,
      "pv_to_grid": 0.0,
      "batt_to_load": 0.0,
      "batt_to_grid": 0.0,
      "grid_to_load": 469.51,
      "grid_to_batt": 0.0,
      "self_consumed": 0.0,
      "self_sufficient": -0.0397,
      "balance_error": 17.91
    },
    {
      "time": "2026-06-23 05:00:00",
      "pv_to_load": 0.0,
      "pv_to_batt": 0.0,
      "pv_to_grid": 0.0,
      "batt_to_load": 0.0,
      "batt_to_grid": 0.0,
      "grid_to_load": 470.09,
      "grid_to_batt": 0.0,
      "self_consumed": 0.0,
      "self_sufficient": 0.0012,
      "balance_error": -0.58
    },
    {
      "time": "2026-06-23 06:00:00",
      "pv_to_load": 0.0,
      "pv_to_batt": 0.0,
      "pv_to_grid": 0.0,
      "batt_to_load": 0.0,
      "batt_to_grid": 0.0,
      "grid_to_load": 474.33,
      "grid_to_batt": 0.0,
      "self_consumed": 0.0,
      "self_sufficient": 0.0852,
      "balance_error": -44.16
    },
    {
      "time": "2026-06-23 07:00:00",
      "pv_to_load": 3.0,
      "pv_to_batt": 0.0,
      "pv_to_grid": 0.0,
      "batt_to_load": 0.0,
      "batt_to_grid": 0.0,
      "grid_to_load": 470.41,
      "grid_to_batt": 0.0,
      "self_consumed": 3.0,
      "self_sufficient": 0.3272,
      "balance_error": -225.79
    },
    {
      "time": "2026-06-23 08:00:00",
      "pv_to_load": 158.0,
      "pv_to_batt": 0.0,
      "pv_to_grid": 0.0,
      "batt_to_load": 0.0,
      "batt_to_grid": 0.0,
      "grid_to_load": 470.38,
      "grid_to_batt": 0.0,
      "self_consumed": 158.0,
      "self_sufficient": 0.3692,
      "balance_error": -117.3
    },
    {
      "time": "2026-06-23 09:00:00",
      "pv_to_load": 382.0,
      "pv_to_batt": 0.0,
      "pv_to_grid": 0.0,
      "batt_to_load": 0.0,
      "batt_to_grid": 0.0,
      "grid_to_load": 453.21,
      "grid_to_batt": 0.0,
      "self_consumed": 382.0,
      "self_sufficient": 0.3765,
      "balance_error": 108.28
    },
    {
      "time": "2026-06-23 10:00:00",
      "pv_to_load": 626.0,
      "pv_to_batt": 0.0,
      "pv_to_grid": 0.0,
      "batt_to_load": 0.0,
      "batt_to_grid": 0.0,
      "grid_to_load": 474.16,
      "grid_to_batt": 0.0,
      "self_consumed": 626.0,
      "self_sufficient": 0.3524,
      "balance_error": 368.01
    },
    {
      "time": "2026-06-23 11:00:00",
      "pv_to_load": 706.0,
      "pv_to_batt": 0.0,
      "pv_to_grid": 0.0,
      "batt_to_load": 0.0,
      "batt_to_grid": 0.0,
      "grid_to_load": 473.74,
      "grid_to_batt": 0.0,
      "self_consumed": 706.0,
      "self_sufficient": 0.3716,
      "balance_error": 425.82
    },
    {
      "time": "2026-06-23 12:00:00",
      "pv_to_load": 542.0,
      "pv_to_batt": 0.0,
      "pv_to_grid": 0.0,
      "batt_to_load": 0.0,
      "batt_to_grid": 0.0,
      "grid_to_load": 407.93,
      "grid_to_batt": 0.0,
      "self_consumed": 542.0,
      "self_sufficient": 0.4775,
      "balance_error": 169.15
    },
    {
      "time": "2026-06-23 13:00:00",
      "pv_to_load": 483.0,
      "pv_to_batt": 0.0,
      "pv_to_grid": 0.0,
      "batt_to_load": 0.0,
      "batt_to_grid": 0.0,
      "grid_to_load": 331.2,
      "grid_to_batt": 0.0,
      "self_consumed": 483.0,
      "self_sufficient": 0.5737,
      "balance_error": 37.23
    },
    {
      "time": "2026-06-23 14:00:00",
      "pv_to_load": 328.0,
      "pv_to_batt": 0.0,
      "pv_to_grid": 0.0,
      "batt_to_load": 0.0,
      "batt_to_grid": 0.0,
      "grid_to_load": 410.83,
      "grid_to_batt": 0.0,
      "self_consumed": 328.0,
      "self_sufficient": 0.4537,
      "balance_error": -13.18
    },
    {
      "time": "2026-06-23 15:00:00",
      "pv_to_load": 175.0,
      "pv_to_batt": 0.0,
      "pv_to_grid": 0.0,
      "batt_to_load": 0.0,
      "batt_to_grid": 0.0,
      "grid_to_load": 470.68,
      "grid_to_batt": 0.0,
      "self_consumed": 175.0,
      "self_sufficient": 0.3722,
      "balance_error": -104.0
    },
    {
      "time": "2026-06-23 16:00:00",
      "pv_to_load": 88.0,
      "pv_to_batt": 0.0,
      "pv_to_grid": 0.0,
      "batt_to_load": 0.0,
      "batt_to_grid": 0.0,
      "grid_to_load": 474.18,
      "grid_to_batt": 0.0,
      "self_consumed": 88.0,
      "self_sufficient": 0.3515,
      "balance_error": -168.99
    },
    {
      "time": "2026-06-23 17:00:00",
      "pv_to_load": 18.0,
      "pv_to_batt": 0.0,
      "pv_to_grid": 0.0,
      "batt_to_load": 0.0,
      "batt_to_grid": 0.0,
      "grid_to_load": 470.12,
      "grid_to_batt": 0.0,
      "self_consumed": 18.0,
      "self_sufficient": 0.3775,
      "balance_error": -267.13
    },
    {
      "time": "2026-06-23 18:00:00",
      "pv_to_load": 0.0,
      "pv_to_batt": 0.0,
      "pv_to_grid": 0.0,
      "batt_to_load": 0.0,
      "batt_to_grid": 0.0,
      "grid_to_load": 111.47,
      "grid_to_batt": 0.0,
      "self_consumed": 0.0,
      "self_sufficient": 0.2776,
      "balance_error": -42.84
    }
  ],
  "irradiation": null,
  "irradiation_forecast": null,
  "financial": null,
  "_mypower24_meta": {
    "serial": "SLV208642208",
    "battery_soc": null
  },
  "prediction_hourly": {
    "p50": [
      {
        "time": "2026-06-23 00:00:00",
        "value": 0.0
      },
      {
        "time": "2026-06-23 01:00:00",
        "value": 0.0
      },
      {
        "time": "2026-06-23 02:00:00",
        "value": 0.0
      },
      {
        "time": "2026-06-23 03:00:00",
        "value": 0.0
      },
      {
        "time": "2026-06-23 04:00:00",
        "value": 0.0
      },
      {
        "time": "2026-06-23 05:00:00",
        "value": 0.0
      },
      {
        "time": "2026-06-23 06:00:00",
        "value": 0.0
      },
      {
        "time": "2026-06-23 07:00:00",
        "value": 0.0
      },
      {
        "time": "2026-06-23 08:00:00",
        "value": 0.0631
      },
      {
        "time": "2026-06-23 09:00:00",
        "value": 0.2402
      },
      {
        "time": "2026-06-23 10:00:00",
        "value": 0.3782
      },
      {
        "time": "2026-06-23 11:00:00",
        "value": 0.5846
      },
      {
        "time": "2026-06-23 12:00:00",
        "value": 0.6063
      },
      {
        "time": "2026-06-23 13:00:00",
        "value": 0.5917
      },
      {
        "time": "2026-06-23 14:00:00",
        "value": 0.4545
      },
      {
        "time": "2026-06-23 15:00:00",
        "value": 0.2786
      },
      {
        "time": "2026-06-23 16:00:00",
        "value": 0.1564
      },
      {
        "time": "2026-06-23 17:00:00",
        "value": 0.0
      },
      {
        "time": "2026-06-23 18:00:00",
        "value": 0.0
      }
    ],
    "p90": [
      {
        "time": "2026-06-23 00:00:00",
        "value": 0.0
      },
      {
        "time": "2026-06-23 01:00:00",
        "value": 0.0
      },
      {
        "time": "2026-06-23 02:00:00",
        "value": 0.0
      },
      {
        "time": "2026-06-23 03:00:00",
        "value": 0.0
      },
      {
        "time": "2026-06-23 04:00:00",
        "value": 0.0
      },
      {
        "time": "2026-06-23 05:00:00",
        "value": 0.0
      },
      {
        "time": "2026-06-23 06:00:00",
        "value": 0.0
      },
      {
        "time": "2026-06-23 07:00:00",
        "value": 0.0
      },
      {
        "time": "2026-06-23 08:00:00",
        "value": 0.0604
      },
      {
        "time": "2026-06-23 09:00:00",
        "value": 0.2297
      },
      {
        "time": "2026-06-23 10:00:00",
        "value": 0.3617
      },
      {
        "time": "2026-06-23 11:00:00",
        "value": 0.559
      },
      {
        "time": "2026-06-23 12:00:00",
        "value": 0.5798
      },
      {
        "time": "2026-06-23 13:00:00",
        "value": 0.5658
      },
      {
        "time": "2026-06-23 14:00:00",
        "value": 0.4346
      },
      {
        "time": "2026-06-23 15:00:00",
        "value": 0.2665
      },
      {
        "time": "2026-06-23 16:00:00",
        "value": 0.1495
      },
      {
        "time": "2026-06-23 17:00:00",
        "value": 0.0
      },
      {
        "time": "2026-06-23 18:00:00",
        "value": 0.0
      }
    ],
    "p95": [
      {
        "time": "2026-06-23 00:00:00",
        "value": 0.0
      },
      {
        "time": "2026-06-23 01:00:00",
        "value": 0.0
      },
      {
        "time": "2026-06-23 02:00:00",
        "value": 0.0
      },
      {
        "time": "2026-06-23 03:00:00",
        "value": 0.0
      },
      {
        "time": "2026-06-23 04:00:00",
        "value": 0.0
      },
      {
        "time": "2026-06-23 05:00:00",
        "value": 0.0
      },
      {
        "time": "2026-06-23 06:00:00",
        "value": 0.0
      },
      {
        "time": "2026-06-23 07:00:00",
        "value": 0.0
      },
      {
        "time": "2026-06-23 08:00:00",
        "value": 0.0596
      },
      {
        "time": "2026-06-23 09:00:00",
        "value": 0.2268
      },
      {
        "time": "2026-06-23 10:00:00",
        "value": 0.3571
      },
      {
        "time": "2026-06-23 11:00:00",
        "value": 0.5519
      },
      {
        "time": "2026-06-23 12:00:00",
        "value": 0.5724
      },
      {
        "time": "2026-06-23 13:00:00",
        "value": 0.5586
      },
      {
        "time": "2026-06-23 14:00:00",
        "value": 0.429
      },
      {
        "time": "2026-06-23 15:00:00",
        "value": 0.263
      },
      {
        "time": "2026-06-23 16:00:00",
        "value": 0.1476
      },
      {
        "time": "2026-06-23 17:00:00",
        "value": 0.0
      },
      {
        "time": "2026-06-23 18:00:00",
        "value": 0.0
      }
    ]
  },
  "prediction_today": {
    "p50": 3.354,
    "p90": 3.207,
    "p95": 3.166
  },
  "performance": {
    "method": "empirical",
    "hourly_expected": [],
    "today_expected_total": 0.0,
    "today_actual_total": 0.0,
    "performance_pct": null,
    "elapsed_hours_compared": 0,
    "reason": "Expected = site's own 30-day average for this hour-of-day"
  }
}
